{
  "checked": 36,
  "failures": [],
  "results": [
    {
      "route": "/",
      "viewport": "desktop",
      "screenshot": "D:\\VsCode\\mahdi law\\law-office-website\\.playwright-cli\\recovery\\desktop-home.png",
      "dir": "rtl",
      "textLength": 32802,
      "links": 30,
      "cards": 35,
      "tables": 0,
      "horizontalOverflow": false
    },
    {
      "route": "/services",
      "viewport": "desktop",
      "screenshot": "D:\\VsCode\\mahdi law\\law-office-website\\.playwright-cli\\recovery\\desktop-services.png",
      "dir": "rtl",
      "textLength": 19029,
      "links": 27,
      "cards": 18,
      "tables": 0,
      "horizontalOverflow": false
    },
    {
      "route": "/services/contract-drafting",
      "viewport": "desktop",
      "screenshot": "D:\\VsCode\\mahdi law\\law-office-website\\.playwright-cli\\recovery\\desktop-services-contract-drafting.png",
      "dir": "rtl",
      "textLength": 19487,
      "links": 27,
      "cards": 18,
      "tables": 0,
      "horizontalOverflow": false
    },
    {
      "route": "/contracts",
      "viewport": "desktop",
      "screenshot": "D:\\VsCode\\mahdi law\\law-office-website\\.playwright-cli\\recovery\\desktop-contracts.png",
      "dir": "rtl",
      "textLength": 20595,
      "links": 26,
      "cards": 17,
      "tables": 0,
      "horizontalOverflow": false
    },
    {
      "route": "/legal-forms",
      "viewport": "desktop",
      "screenshot": "D:\\VsCode\\mahdi law\\law-office-website\\.playwright-cli\\recovery\\desktop-legal-forms.png",
      "dir": "rtl",
      "textLength": 18363,
      "links": 26,
      "cards": 15,
      "tables": 0,
      "horizontalOverflow": false
    },
    {
      "route": "/requests/new",
      "viewport": "desktop",
      "screenshot": "D:\\VsCode\\mahdi law\\law-office-website\\.playwright-cli\\recovery\\desktop-requests-new.png",
      "dir": "rtl",
      "textLength": 22862,
      "links": 26,
      "cards": 16,
      "tables": 0,
      "horizontalOverflow": false
    },
    {
      "route": "/admin/requests",
      "viewport": "desktop",
      "screenshot": "D:\\VsCode\\mahdi law\\law-office-website\\.playwright-cli\\recovery\\desktop-admin-requests.png",
      "dir": "rtl",
      "textLength": 13115,
      "links": 5,
      "cards": 6,
      "tables": 1,
      "horizontalOverflow": false
    },
    {
      "route": "/admin/legal-forms",
      "viewport": "desktop",
      "screenshot": "D:\\VsCode\\mahdi law\\law-office-website\\.playwright-cli\\recovery\\desktop-admin-legal-forms.png",
      "dir": "rtl",
      "textLength": 12775,
      "links": 5,
      "cards": 5,
      "tables": 0,
      "horizontalOverflow": false
    },
    {
      "route": "/admin/faqs",
      "viewport": "desktop",
      "screenshot": "D:\\VsCode\\mahdi law\\law-office-website\\.playwright-cli\\recovery\\desktop-admin-faqs.png",
      "dir": "rtl",
      "textLength": 12941,
      "links": 5,
      "cards": 3,
      "tables": 0,
      "horizontalOverflow": false
    },
    {
      "route": "/dashboard",
      "viewport": "desktop",
      "screenshot": "D:\\VsCode\\mahdi law\\law-office-website\\.playwright-cli\\recovery\\desktop-dashboard.png",
      "dir": "rtl",
      "textLength": 10484,
      "links": 22,
      "cards": 27,
      "tables": 1,
      "horizontalOverflow": false
    },
    {
      "route": "/dashboard/documents",
      "viewport": "desktop",
      "screenshot": "D:\\VsCode\\mahdi law\\law-office-website\\.playwright-cli\\recovery\\desktop-dashboard-documents.png",
      "dir": "rtl",
      "textLength": 10266,
      "links": 11,
      "cards": 14,
      "tables": 1,
      "horizontalOverflow": false
    },
    {
      "route": "/dashboard/signatures",
      "viewport": "desktop",
      "screenshot": "D:\\VsCode\\mahdi law\\law-office-website\\.playwright-cli\\recovery\\desktop-dashboard-signatures.png",
      "dir": "rtl",
      "textLength": 10329,
      "links": 14,
      "cards": 12,
      "tables": 0,
      "horizontalOverflow": false
    },
    {
      "route": "/",
      "viewport": "tablet",
      "screenshot": "D:\\VsCode\\mahdi law\\law-office-website\\.playwright-cli\\recovery\\tablet-home.png",
      "dir": "rtl",
      "textLength": 32802,
      "links": 30,
      "cards": 35,
      "tables": 0,
      "horizontalOverflow": false
    },
    {
      "route": "/services",
      "viewport": "tablet",
      "screenshot": "D:\\VsCode\\mahdi law\\law-office-website\\.playwright-cli\\recovery\\tablet-services.png",
      "dir": "rtl",
      "textLength": 19029,
      "links": 27,
      "cards": 18,
      "tables": 0,
      "horizontalOverflow": false
    },
    {
      "route": "/services/contract-drafting",
      "viewport": "tablet",
      "screenshot": "D:\\VsCode\\mahdi law\\law-office-website\\.playwright-cli\\recovery\\tablet-services-contract-drafting.png",
      "dir": "rtl",
      "textLength": 19487,
      "links": 27,
      "cards": 18,
      "tables": 0,
      "horizontalOverflow": false
    },
    {
      "route": "/contracts",
      "viewport": "tablet",
      "screenshot": "D:\\VsCode\\mahdi law\\law-office-website\\.playwright-cli\\recovery\\tablet-contracts.png",
      "dir": "rtl",
      "textLength": 20595,
      "links": 26,
      "cards": 17,
      "tables": 0,
      "horizontalOverflow": false
    },
    {
      "route": "/legal-forms",
      "viewport": "tablet",
      "screenshot": "D:\\VsCode\\mahdi law\\law-office-website\\.playwright-cli\\recovery\\tablet-legal-forms.png",
      "dir": "rtl",
      "textLength": 18363,
      "links": 26,
      "cards": 15,
      "tables": 0,
      "horizontalOverflow": false
    },
    {
      "route": "/requests/new",
      "viewport": "tablet",
      "screenshot": "D:\\VsCode\\mahdi law\\law-office-website\\.playwright-cli\\recovery\\tablet-requests-new.png",
      "dir": "rtl",
      "textLength": 22862,
      "links": 26,
      "cards": 16,
      "tables": 0,
      "horizontalOverflow": false
    },
    {
      "route": "/admin/requests",
      "viewport": "tablet",
      "screenshot": "D:\\VsCode\\mahdi law\\law-office-website\\.playwright-cli\\recovery\\tablet-admin-requests.png",
      "dir": "rtl",
      "textLength": 13115,
      "links": 5,
      "cards": 6,
      "tables": 1,
      "horizontalOverflow": false
    },
    {
      "route": "/admin/legal-forms",
      "viewport": "tablet",
      "screenshot": "D:\\VsCode\\mahdi law\\law-office-website\\.playwright-cli\\recovery\\tablet-admin-legal-forms.png",
      "dir": "rtl",
      "textLength": 12775,
      "links": 5,
      "cards": 5,
      "tables": 0,
      "horizontalOverflow": false
    },
    {
      "route": "/admin/faqs",
      "viewport": "tablet",
      "screenshot": "D:\\VsCode\\mahdi law\\law-office-website\\.playwright-cli\\recovery\\tablet-admin-faqs.png",
      "dir": "rtl",
      "textLength": 12941,
      "links": 5,
      "cards": 3,
      "tables": 0,
      "horizontalOverflow": false
    },
    {
      "route": "/dashboard",
      "viewport": "tablet",
      "screenshot": "D:\\VsCode\\mahdi law\\law-office-website\\.playwright-cli\\recovery\\tablet-dashboard.png",
      "dir": "rtl",
      "textLength": 10484,
      "links": 22,
      "cards": 27,
      "tables": 1,
      "horizontalOverflow": false
    },
    {
      "route": "/dashboard/documents",
      "viewport": "tablet",
      "screenshot": "D:\\VsCode\\mahdi law\\law-office-website\\.playwright-cli\\recovery\\tablet-dashboard-documents.png",
      "dir": "rtl",
      "textLength": 10266,
      "links": 11,
      "cards": 14,
      "tables": 1,
      "horizontalOverflow": false
    },
    {
      "route": "/dashboard/signatures",
      "viewport": "tablet",
      "screenshot": "D:\\VsCode\\mahdi law\\law-office-website\\.playwright-cli\\recovery\\tablet-dashboard-signatures.png",
      "dir": "rtl",
      "textLength": 10329,
      "links": 14,
      "cards": 12,
      "tables": 0,
      "horizontalOverflow": false
    },
    {
      "route": "/",
      "viewport": "mobile",
      "screenshot": "D:\\VsCode\\mahdi law\\law-office-website\\.playwright-cli\\recovery\\mobile-home.png",
      "dir": "rtl",
      "textLength": 32802,
      "links": 30,
      "cards": 35,
      "tables": 0,
      "horizontalOverflow": false
    },
    {
      "route": "/services",
      "viewport": "mobile",
      "screenshot": "D:\\VsCode\\mahdi law\\law-office-website\\.playwright-cli\\recovery\\mobile-services.png",
      "dir": "rtl",
      "textLength": 19029,
      "links": 27,
      "cards": 18,
      "tables": 0,
      "horizontalOverflow": false
    },
    {
      "route": "/services/contract-drafting",
      "viewport": "mobile",
      "screenshot": "D:\\VsCode\\mahdi law\\law-office-website\\.playwright-cli\\recovery\\mobile-services-contract-drafting.png",
      "dir": "rtl",
      "textLength": 19487,
      "links": 27,
      "cards": 18,
      "tables": 0,
      "horizontalOverflow": false
    },
    {
      "route": "/contracts",
      "viewport": "mobile",
      "screenshot": "D:\\VsCode\\mahdi law\\law-office-website\\.playwright-cli\\recovery\\mobile-contracts.png",
      "dir": "rtl",
      "textLength": 20595,
      "links": 26,
      "cards": 17,
      "tables": 0,
      "horizontalOverflow": false
    },
    {
      "route": "/legal-forms",
      "viewport": "mobile",
      "screenshot": "D:\\VsCode\\mahdi law\\law-office-website\\.playwright-cli\\recovery\\mobile-legal-forms.png",
      "dir": "rtl",
      "textLength": 18363,
      "links": 26,
      "cards": 15,
      "tables": 0,
      "horizontalOverflow": false
    },
    {
      "route": "/requests/new",
      "viewport": "mobile",
      "screenshot": "D:\\VsCode\\mahdi law\\law-office-website\\.playwright-cli\\recovery\\mobile-requests-new.png",
      "dir": "rtl",
      "textLength": 22862,
      "links": 26,
      "cards": 16,
      "tables": 0,
      "horizontalOverflow": false
    },
    {
      "route": "/admin/requests",
      "viewport": "mobile",
      "screenshot": "D:\\VsCode\\mahdi law\\law-office-website\\.playwright-cli\\recovery\\mobile-admin-requests.png",
      "dir": "rtl",
      "textLength": 13115,
      "links": 5,
      "cards": 6,
      "tables": 1,
      "horizontalOverflow": false
    },
    {
      "route": "/admin/legal-forms",
      "viewport": "mobile",
      "screenshot": "D:\\VsCode\\mahdi law\\law-office-website\\.playwright-cli\\recovery\\mobile-admin-legal-forms.png",
      "dir": "rtl",
      "textLength": 12775,
      "links": 5,
      "cards": 5,
      "tables": 0,
      "horizontalOverflow": false
    },
    {
      "route": "/admin/faqs",
      "viewport": "mobile",
      "screenshot": "D:\\VsCode\\mahdi law\\law-office-website\\.playwright-cli\\recovery\\mobile-admin-faqs.png",
      "dir": "rtl",
      "textLength": 12941,
      "links": 5,
      "cards": 3,
      "tables": 0,
      "horizontalOverflow": false
    },
    {
      "route": "/dashboard",
      "viewport": "mobile",
      "screenshot": "D:\\VsCode\\mahdi law\\law-office-website\\.playwright-cli\\recovery\\mobile-dashboard.png",
      "dir": "rtl",
      "textLength": 10484,
      "links": 22,
      "cards": 27,
      "tables": 1,
      "horizontalOverflow": false
    },
    {
      "route": "/dashboard/documents",
      "viewport": "mobile",
      "screenshot": "D:\\VsCode\\mahdi law\\law-office-website\\.playwright-cli\\recovery\\mobile-dashboard-documents.png",
      "dir": "rtl",
      "textLength": 10266,
      "links": 11,
      "cards": 14,
      "tables": 1,
      "horizontalOverflow": false
    },
    {
      "route": "/dashboard/signatures",
      "viewport": "mobile",
      "screenshot": "D:\\VsCode\\mahdi law\\law-office-website\\.playwright-cli\\recovery\\mobile-dashboard-signatures.png",
      "dir": "rtl",
      "textLength": 10329,
      "links": 14,
      "cards": 12,
      "tables": 0,
      "horizontalOverflow": false
    }
  ]
}